.gitignore
MANIFEST.in
README.txt
setup.cfg
setup.py
docs/HISTORY.txt
rbco/__init__.py
rbco.wfdocumentator.egg-info/PKG-INFO
rbco.wfdocumentator.egg-info/SOURCES.txt
rbco.wfdocumentator.egg-info/dependency_links.txt
rbco.wfdocumentator.egg-info/entry_points.txt
rbco.wfdocumentator.egg-info/namespace_packages.txt
rbco.wfdocumentator.egg-info/not-zip-safe
rbco.wfdocumentator.egg-info/requires.txt
rbco.wfdocumentator.egg-info/top_level.txt
rbco/wfdocumentator/__init__.py
rbco/wfdocumentator/configure.zcml
rbco/wfdocumentator/interfaces.py
rbco/wfdocumentator/util.py
rbco/wfdocumentator/validation.py
rbco/wfdocumentator/wfdesc.py
rbco/wfdocumentator/wfgraph.py
rbco/wfdocumentator/browser/__init__.py
rbco/wfdocumentator/browser/configure.zcml
rbco/wfdocumentator/browser/views.py
rbco/wfdocumentator/browser/wfdoc.pt
rbco/wfdocumentator/locales/pt_BR/LC_MESSAGES/plone.po