Metadata-Version: 1.1
Name: rbco.wfdocumentator
Version: 1.0.0
Summary: An add-on for Zope and Plone which aims to provide user-friendly automatically generated documentation about workflow definitions.
Home-page: https://github.com/rafaelbco/rbco.wfdocumentator
Author: Rafael Oliveira
Author-email: rafaelbco@gmail.com
License: GPL
Keywords: plone workflow
Platform: UNKNOWN
Classifier: Framework :: Plone
Classifier: Programming Language :: Python :: 2.7
Classifier: Programming Language :: Python
Classifier: Topic :: Software Development :: Libraries :: Python Modules
